{
  "ACE": {
    "mean": 8.492789848498568,
    "std": 4.892305788881418,
    "n": 269
  },
  "DSN": {
    "mean": 0.0,
    "std": 0.0,
    "n": 4672
  },
  "DSS": {
    "mean": 0.0,
    "std": 0.0,
    "n": 1202
  },
  "JWST": {
    "mean": 10.818296962577183,
    "std": 5.925530924314101,
    "n": 566
  },
  "KPLO": {
    "mean": 8.483538724315205,
    "std": 6.471025004669139,
    "n": 477
  },
  "LUCY": {
    "mean": 8.83848630414718,
    "std": 4.369458637621367,
    "n": 489
  },
  "M01O": {
    "mean": 8.16837856483101,
    "std": 4.103846182963808,
    "n": 927
  },
  "MMS2": {
    "mean": 12.105138305968476,
    "std": 5.474921473560757,
    "n": 118
  },
  "ORX": {
    "mean": 4.111897588788788,
    "std": 6.2894856006493995,
    "n": 187
  },
  "SOHO": {
    "mean": 10.31975232665257,
    "std": 4.6462369408423845,
    "n": 712
  },
  "SPP": {
    "mean": 7.972432685974844,
    "std": 4.251255724617732,
    "n": 413
  },
  "VGR2": {
    "mean": 4.367360266712752,
    "std": 1.6813657696891042,
    "n": 392
  },
  "CAPS": {
    "mean": 8.567011311619995,
    "std": 5.813276709726677,
    "n": 127
  },
  "MRO": {
    "mean": 11.205071315020867,
    "std": 5.898485753910274,
    "n": 463
  },
  "STA": {
    "mean": 10.477120085128659,
    "std": 5.335564058824142,
    "n": 282
  },
  "IMAP": {
    "mean": 10.46651067587604,
    "std": 5.624427319989512,
    "n": 183
  },
  "MMS3": {
    "mean": 11.762863370094127,
    "std": 5.72781504622732,
    "n": 115
  },
  "TGO": {
    "mean": 9.887044865277801,
    "std": 5.471309018873762,
    "n": 124
  },
  "TDR8": {
    "mean": 6.839711603308979,
    "std": 3.15492915596383,
    "n": 114
  },
  "MMS4": {
    "mean": 12.13941627223648,
    "std": 5.47106358190243,
    "n": 89
  },
  "WIND": {
    "mean": 8.007963947833304,
    "std": 4.088131133309175,
    "n": 231
  },
  "ESCB": {
    "mean": 8.186738073100116,
    "std": 3.2098915480235064,
    "n": 150
  },
  "THC": {
    "mean": 8.38924998544966,
    "std": 5.453111093487148,
    "n": 78
  },
  "CHDR": {
    "mean": 8.007681517661823,
    "std": 6.912538492819951,
    "n": 267
  },
  "MMS1": {
    "mean": 10.4652553904509,
    "std": 6.488924213011891,
    "n": 119
  },
  "ESCG": {
    "mean": 8.077526891985158,
    "std": 3.1640847358264295,
    "n": 162
  },
  "VGR1": {
    "mean": 4.480787283015591,
    "std": 1.6403641943256457,
    "n": 330
  },
  "DSSR": {
    "mean": 0.0,
    "std": 0.0,
    "n": 78
  },
  "LRO": {
    "mean": 10.032220809621018,
    "std": 6.776313845958997,
    "n": 224
  },
  "SWFO": {
    "mean": 0.0,
    "std": 0.0,
    "n": 89
  },
  "GBRA": {
    "mean": 0.0,
    "std": 0.0,
    "n": 290
  },
  "EMM": {
    "mean": 11.325697287323143,
    "std": 3.5141971093333795,
    "n": 57
  },
  "TESS": {
    "mean": 7.8961054935292045,
    "std": 5.4536603638678,
    "n": 73
  },
  "EURC": {
    "mean": 6.147559529759076,
    "std": 5.361401561922815,
    "n": 131
  },
  "NHPC": {
    "mean": 0.0,
    "std": 0.0,
    "n": 18
  },
  "PSYC": {
    "mean": 10.396395383131207,
    "std": 4.958925136755669,
    "n": 286
  },
  "JNO": {
    "mean": 8.94779033463647,
    "std": 4.49965960594497,
    "n": 688
  },
  "MSL": {
    "mean": 0.22657582266708873,
    "std": 1.0717669374052543,
    "n": 70
  },
  "M20": {
    "mean": 0.34507664883825534,
    "std": 1.2911585921288549,
    "n": 60
  },
  "CGO": {
    "mean": 10.07358550123828,
    "std": 5.6489869174831435,
    "n": 127
  },
  "BIOS": {
    "mean": 7.475687476382571,
    "std": 3.4038750077057762,
    "n": 35
  },
  "SGP": {
    "mean": 0.0,
    "std": 0.0,
    "n": 34
  },
  "DSCO": {
    "mean": 3.961415020514468,
    "std": 4.8517227298287,
    "n": 15
  },
  "THB": {
    "mean": 8.981432174460899,
    "std": 5.298115455926482,
    "n": 47
  },
  "MMX": {
    "mean": 5.784885711142975,
    "std": 4.886808177476845,
    "n": 52
  },
  "RST": {
    "mean": 8.091586331914513,
    "std": 5.869664019498173,
    "n": 19
  },
  "XMM": {
    "mean": 10.096105009505944,
    "std": 3.4834871754517813,
    "n": 47
  },
  "TEST": {
    "mean": 0.0,
    "std": 0.0,
    "n": 45
  },
  "MEX": {
    "mean": 9.286634546249735,
    "std": 4.918249063499639,
    "n": 23
  },
  "BEPI": {
    "mean": 6.2961023683473805,
    "std": 3.365408276344554,
    "n": 9
  },
  "HYB2": {
    "mean": 0.0,
    "std": 0.0,
    "n": 4
  },
  "HCRA": {
    "mean": 0.0,
    "std": 0.0,
    "n": 11
  }
}